usdm4_fhir/__info__.py
usdm4_fhir/__init__.py
usdm4_fhir/__version__.py
usdm4_fhir/errors/__init__.py
usdm4_fhir/errors/errors.py
usdm4_fhir/factory/__init__.py
usdm4_fhir/factory/activity_definition_factory.py
usdm4_fhir/factory/address_factory.py
usdm4_fhir/factory/associated_party_factory.py
usdm4_fhir/factory/base_factory.py
usdm4_fhir/factory/bundle_entry_factory.py
usdm4_fhir/factory/bundle_factory.py
usdm4_fhir/factory/cdisc_fhir.py
usdm4_fhir/factory/codeable_concept_factory.py
usdm4_fhir/factory/coding_factory.py
usdm4_fhir/factory/composition_factory.py
usdm4_fhir/factory/extension_factory.py
usdm4_fhir/factory/group_factory.py
usdm4_fhir/factory/identifier_factory.py
usdm4_fhir/factory/iso8601_ucum.py
usdm4_fhir/factory/label_type_factory.py
usdm4_fhir/factory/medicinal_product_factory.py
usdm4_fhir/factory/organization_factory.py
usdm4_fhir/factory/plan_definition_action_factory.py
usdm4_fhir/factory/plan_definition_factory.py
usdm4_fhir/factory/plan_definition_related_action_factory.py
usdm4_fhir/factory/progress_status_factory.py
usdm4_fhir/factory/reference_factory.py
usdm4_fhir/factory/research_study_factory.py
usdm4_fhir/factory/research_study_factory_p3.py
usdm4_fhir/factory/study_url.py
usdm4_fhir/factory/timeline_plan_definition_factory.py
usdm4_fhir/factory/timepoint_plan_definition_factory.py
usdm4_fhir/factory/urn_uuid.py
usdm4_fhir/m11/__init__.py
usdm4_fhir/m11/export/__init__.py
usdm4_fhir/m11/export/export.py
usdm4_fhir/m11/export/export_base.py
usdm4_fhir/m11/export/export_madrid.py
usdm4_fhir/m11/export/export_prism2.py
usdm4_fhir/m11/export/export_prism3.py
usdm4_fhir/m11/import_/__init__.py
usdm4_fhir/m11/import_/import_prism2.py
usdm4_fhir/m11/import_/import_prism3.py
usdm4_fhir/m11/import_/title_page.py
usdm4_fhir/m11/utility/__init__.py
usdm4_fhir/m11/utility/address_service.py
usdm4_fhir/m11/utility/soup.py
usdm4_fhir/m11/utility/tag_reference.py
usdm4_fhir/soa/__init__.py
usdm4_fhir/soa/export/__init__.py
usdm4_fhir-0.6.3.dist-info/licenses/LICENSE
usdm4_fhir-0.6.3.dist-info/METADATA
usdm4_fhir-0.6.3.dist-info/WHEEL
usdm4_fhir-0.6.3.dist-info/top_level.txt
usdm4_fhir-0.6.3.dist-info/RECORD
