Metadata-Version: 2.4
Name: usdm4_fhir
Version: 0.6.3
Summary: A python package for importing and exporting the CDISC TransCelerate USDM, version 4, using Excel
Author: D Iberson-Hurst
Author-email: 
Classifier: Intended Audience :: Developers
Classifier: Programming Language :: Python
Classifier: Programming Language :: Python :: 3
Classifier: Programming Language :: Python :: 3.10
Classifier: Operating System :: OS Independent
License-File: LICENSE
Requires-Dist: usdm4>=0.13.1
Requires-Dist: d4k_ms_base>=0.3.0
Requires-Dist: openpyxl
Dynamic: author
Dynamic: classifier
Dynamic: description
Dynamic: description-content-type
Dynamic: license-file
Dynamic: requires-dist
Dynamic: summary
